pkg_test_random/__init__.py
pkg_test_random/test.py
pkg_test_random-0.1.0.dist-info/METADATA
pkg_test_random-0.1.0.dist-info/WHEEL
pkg_test_random-0.1.0.dist-info/top_level.txt
pkg_test_random-0.1.0.dist-info/RECORD
